[
	{
		"path": "$ROOTPATH$/C-with-Hindley-Milner-Type-System/src/Language/C/Parser/Parser.y",
		"bookmarks": [
			{
				"line": 262,
				"column": 8,
				"label": "CHM Tokens"
			},
			{
				"line": 2166,
				"column": 6,
				"label": "CHM Rules"
			}
		]
	},
	{
		"path": "$ROOTPATH$/C-with-Hindley-Milner-Type-System/src/Language/C/Pretty.hs",
		"bookmarks": [
			{
				"line": 96,
				"column": 1,
				"label": "CHM Pretty CExtDecl"
			},
			{
				"line": 557,
				"column": 6,
				"label": "CHM Pretty"
			}
		]
	},
	{
		"path": "$ROOTPATH$/C-with-Hindley-Milner-Type-System/src/Language/C/Parser/Lexer.x",
		"bookmarks": [
			{
				"line": 425,
				"column": 16,
				"label": "CHM Token  Lex"
			}
		]
	}
]